rws_client-0.1.4.dist-info/METADATA
rws_client-0.1.4.dist-info/WHEEL
rws/__init__.py
rws/client.py
rws/typing.py
rws/__init__.pyi
rws/_rws.cpython-311-x86_64-linux-gnu.so
rws_client-0.1.4.dist-info/RECORD
