Metadata-Version: 2.4
Name: rws-client
Version: 0.1.4
Classifier: Development Status :: 4 - Beta
Classifier: Intended Audience :: Developers
Classifier: License :: OSI Approved :: MIT License
Classifier: Operating System :: OS Independent
Classifier: Programming Language :: Python :: 3
Classifier: Programming Language :: Python :: 3.11
Classifier: Programming Language :: Rust
Classifier: Topic :: Software Development :: Libraries :: Python Modules
Requires-Dist: typing-extensions>=4.0.0
Requires-Dist: ruff>=0.1.3 ; extra == 'dev'
Requires-Dist: pytest>=7.4.2 ; extra == 'dev'
Requires-Dist: pytest-asyncio>=0.21.1 ; extra == 'dev'
Requires-Dist: maturin>=1.0.0 ; extra == 'dev'
Provides-Extra: dev
Summary: WebSocket client with Rust backend
Author-email: Your Name <your.email@example.com>
Requires-Python: >=3.11
